bugwarrior/README.rst
bugwarrior/__init__.py
bugwarrior/collect.py
bugwarrior/command.py
bugwarrior/db.py
bugwarrior/notifications.py
bugwarrior/config/__init__.py
bugwarrior/config/data.py
bugwarrior/config/ini2toml_plugin.py
bugwarrior/config/load.py
bugwarrior/config/schema.py
bugwarrior/config/secrets.py
bugwarrior/docs/automatic_updates.rst
bugwarrior/docs/common_configuration.rst
bugwarrior/docs/conf.py
bugwarrior/docs/contributing.rst
bugwarrior/docs/faq.rst
bugwarrior/docs/generate_service_template.py
bugwarrior/docs/getting.rst
bugwarrior/docs/index.rst
bugwarrior/docs/manpage.rst
bugwarrior/docs/other_services.rst
bugwarrior/docs/services.rst
bugwarrior/docs/using.rst
bugwarrior/docs/_ext/config.py
bugwarrior/docs/_ext/extras.py
bugwarrior/docs/_ext/udas.py
bugwarrior/docs/other-services/api.rst
bugwarrior/docs/other-services/third_party.rst
bugwarrior/docs/other-services/tutorial.rst
bugwarrior/docs/services/azuredevops.rst
bugwarrior/docs/services/bitbucket.rst
bugwarrior/docs/services/bts.rst
bugwarrior/docs/services/bugzilla.rst
bugwarrior/docs/services/clickup.rst
bugwarrior/docs/services/deck.rst
bugwarrior/docs/services/gerrit.rst
bugwarrior/docs/services/gitbug.rst
bugwarrior/docs/services/github.rst
bugwarrior/docs/services/gitlab.rst
bugwarrior/docs/services/gmail.rst
bugwarrior/docs/services/jira.rst
bugwarrior/docs/services/kanboard.rst
bugwarrior/docs/services/linear.rst
bugwarrior/docs/services/logseq.rst
bugwarrior/docs/services/pagure.rst
bugwarrior/docs/services/phabricator.rst
bugwarrior/docs/services/pivotaltracker.rst
bugwarrior/docs/services/redmine.rst
bugwarrior/docs/services/taiga.rst
bugwarrior/docs/services/teamwork_projects.rst
bugwarrior/docs/services/todoist.rst
bugwarrior/docs/services/trac.rst
bugwarrior/docs/services/trello.rst
bugwarrior/docs/services/youtrack.rst
bugwarrior/services/__init__.py
bugwarrior/services/azuredevops.py
bugwarrior/services/bitbucket.py
bugwarrior/services/bts.py
bugwarrior/services/bz.py
bugwarrior-2.1.0.dist-info/licenses/LICENSE.txt
bugwarrior-2.1.0.dist-info/METADATA
bugwarrior-2.1.0.dist-info/WHEEL
bugwarrior-2.1.0.dist-info/entry_points.txt
bugwarrior-2.1.0.dist-info/top_level.txt
bugwarrior-2.1.0.dist-info/RECORD
